setup.py
dsnd_probability_JG/Binomialdistribution.py
dsnd_probability_JG/Gaussiandistribution.py
dsnd_probability_JG/Generaldistribution.py
dsnd_probability_JG/__init__.py
dsnd_probability_JG.egg-info/PKG-INFO
dsnd_probability_JG.egg-info/SOURCES.txt
dsnd_probability_JG.egg-info/dependency_links.txt
dsnd_probability_JG.egg-info/not-zip-safe
dsnd_probability_JG.egg-info/top_level.txt