Metadata-Version: 1.0
Name: dsnd-probability-JG
Version: 0.1
Summary: Gaussian and Binomial distributions
Home-page: UNKNOWN
Author: Joao Granja
Author-email: jgranja10+JG@gmail.com
License: UNKNOWN
Platform: UNKNOWN
